polvon/__init__.py
polvon/main.py
polvon/service.py
polvon/tui.py
polvon-0.1.2.dist-info/licenses/LICENSE
polvon-0.1.2.dist-info/METADATA
polvon-0.1.2.dist-info/WHEEL
polvon-0.1.2.dist-info/entry_points.txt
polvon-0.1.2.dist-info/top_level.txt
polvon-0.1.2.dist-info/RECORD
