Metadata-Version: 2.4
Name: polvon
Version: 0.1.2
Summary: CLI tool for managing Linux systemd services, apps, and automations
Author: Sayfulla Mirkhalikov
License-Expression: MIT
Project-URL: Homepage, https://github.com/thesayfulla/polvon
Project-URL: Repository, https://github.com/thesayfulla/polvon
Keywords: systemd,cli,tui,service-manager
Classifier: Development Status :: 3 - Alpha
Classifier: Intended Audience :: System Administrators
Classifier: Programming Language :: Python :: 3
Classifier: Programming Language :: Python :: 3.8
Classifier: Programming Language :: Python :: 3.9
Classifier: Programming Language :: Python :: 3.10
Classifier: Programming Language :: Python :: 3.11
Classifier: Programming Language :: Python :: 3.12
Classifier: Topic :: System :: Systems Administration
Requires-Python: >=3.8
License-File: LICENSE
Requires-Dist: textual>=0.47.0
Requires-Dist: rich>=13.0.0
Dynamic: license-file
